gradio_customcode/__init__.py
gradio_customcode/customcode.py
gradio_customcode/customcode.pyi
gradio_customcode/datamodel.py
gradio_customcode/templates/component/Index-DDP5BmnT.js
gradio_customcode/templates/component/clike-DxjBFHnq.js
gradio_customcode/templates/component/dockerfile-CEE6bo6a.js
gradio_customcode/templates/component/frontmatter-DiNESaF0.js
gradio_customcode/templates/component/index-C8HBvtkY.js
gradio_customcode/templates/component/index-CN58gyvS.js
gradio_customcode/templates/component/index-D4oUxMMF.js
gradio_customcode/templates/component/index-D8__MQ5g.js
gradio_customcode/templates/component/index-HvlXv95d.js
gradio_customcode/templates/component/index-UfjmCawP.js
gradio_customcode/templates/component/index-j4FzfPPU.js
gradio_customcode/templates/component/index-mZfy39OJ.js
gradio_customcode/templates/component/index.js
gradio_customcode/templates/component/r-Bz1d3XP0.js
gradio_customcode/templates/component/shell-C0C2sNA_.js
gradio_customcode/templates/component/sql-uoWIYwDX.js
gradio_customcode/templates/component/style.css
gradio_customcode/templates/component/yaml-Dt6Tp2eU.js
gradio_customcode/templates/example/index.js
gradio_customcode/templates/example/style.css
gradio_customcode-0.0.4.dist-info/METADATA
gradio_customcode-0.0.4.dist-info/WHEEL
gradio_customcode-0.0.4.dist-info/RECORD
